test_time_training.cpython-312-x86_64-linux-gnu.so
test_time_training.libs/libcuda-83126a9e.so.550.90.07
test_time_training.libs/libcudart-3de79bdf.so.12.8.57
test_time_training-0.9.0.dist-info/LICENSE
test_time_training-0.9.0.dist-info/METADATA
test_time_training-0.9.0.dist-info/WHEEL
test_time_training-0.9.0.dist-info/top_level.txt
test_time_training-0.9.0.dist-info/RECORD
