Metadata-Version: 2.2
Name: test_time_training
Version: 0.9.0
Summary: A library for test-time training.
Home-page: https://github.com/koceja/TTT-tk
Author: Daniel Koceja
Author-email: dankoceja@gmail.com
License-File: LICENSE
Requires-Dist: torch>=2.4.0
Requires-Dist: numpy
Dynamic: author
Dynamic: author-email
Dynamic: description
Dynamic: description-content-type
Dynamic: home-page
Dynamic: requires-dist
Dynamic: summary
